odoo/addons/account_check_deposit_operating_unit/README.rst
odoo/addons/account_check_deposit_operating_unit/__init__.py
odoo/addons/account_check_deposit_operating_unit/__manifest__.py
odoo/addons/account_check_deposit_operating_unit/i18n/account_check_deposit_operating_unit.pot
odoo/addons/account_check_deposit_operating_unit/models/__init__.py
odoo/addons/account_check_deposit_operating_unit/models/check_deposit.py
odoo/addons/account_check_deposit_operating_unit/readme/CONTRIBUTORS.rst
odoo/addons/account_check_deposit_operating_unit/readme/DESCRIPTION.rst
odoo/addons/account_check_deposit_operating_unit/readme/USAGE.rst
odoo/addons/account_check_deposit_operating_unit/security/check_deposit_security.xml
odoo/addons/account_check_deposit_operating_unit/static/description/icon.png
odoo/addons/account_check_deposit_operating_unit/static/description/index.html
odoo/addons/account_check_deposit_operating_unit/views/check_deposit_views.xml
odoo13_addon_account_check_deposit_operating_unit-13.0.1.0.1.dev2.dist-info/METADATA
odoo13_addon_account_check_deposit_operating_unit-13.0.1.0.1.dev2.dist-info/WHEEL
odoo13_addon_account_check_deposit_operating_unit-13.0.1.0.1.dev2.dist-info/top_level.txt
odoo13_addon_account_check_deposit_operating_unit-13.0.1.0.1.dev2.dist-info/RECORD
