Metadata-Version: 2.1
Name: odoo13-addon-account-check-deposit-operating-unit
Version: 13.0.1.0.1.dev2
Summary: Operating Unit in Check Deposit
Home-page: https://github.com/OCA/operating-unit
Author: Ecosoft, Odoo Community Association (OCA)
Author-email: support@odoo-community.org
License: AGPL-3
Platform: UNKNOWN
Classifier: Programming Language :: Python
Classifier: Framework :: Odoo
Classifier: Framework :: Odoo :: 13.0
Classifier: License :: OSI Approved :: GNU Affero General Public License v3
Requires-Python: >=3.5
Requires-Dist: odoo13-addon-account-check-deposit
Requires-Dist: odoo13-addon-account-operating-unit
Requires-Dist: odoo <13.1dev,>=13.0a
